{"params": {"level": 23,"timelimit": 68695,"initialscore": 14,"targetscore": 49,"lanespeed": 0.6256230572169669},"entities": [{"type": "brick","time": 1000,"x": 1.0,"value": 20},{"type": "dot","time": 1319,"x": 0.15060481384344004,"value": 9},{"type": "brick","time": 1638,"x": 1.0,"value": 19},{"type": "brick","time": 1957,"x": 1.0,"value": 19},{"type": "dot","time": 2276,"x": 0.46413511145001807,"value": 7},{"type": "brick","time": 2595,"x": 0.3333333333333333,"value": 6},{"type": "dot","time": 2914,"x": 0.3362990824307388,"value": 9},{"type": "dot","time": 3233,"x": 0.4256804424682691,"value": 2},{"type": "brick","time": 3552,"x": 0.0,"value": 9},{"type": "dot","time": 3871,"x": 0.40431073956864216,"value": 7},{"type": "dot","time": 4190,"x": 0.011295010212989287,"value": 6},{"type": "brick","time": 4509,"x": 0.0,"value": 9},{"type": "dot","time": 4828,"x": 0.879257158175989,"value": 4},{"type": "dot","time": 5147,"x": 0.27747472090835,"value": 8},{"type": "barrier","time": 5466,"x": 0.5,"height": 2167},{"type": "brick","time": 5785,"x": 0.3333333333333333,"value": 17},{"type": "brick","time": 6104,"x": 0.3333333333333333,"value": 7},{"type": "barrier","time": 6423,"x": 0.5,"height": 962},{"type": "dot","time": 6742,"x": 0.04466437930608336,"value": 2},{"type": "barrier","time": 7061,"x": 0.5,"height": 2745},{"type": "dot","time": 7380,"x": 0.27687009503010895,"value": 4},{"type": "brick","time": 7699,"x": 0.0,"value": 6},{"type": "brick","time": 7699,"x": 0.3333333333333333,"value": 20},{"type": "brick","time": 7699,"x": 0.6666666666666666,"value": 1},{"type": "brick","time": 7699,"x": 1.0,"value": 7},{"type": "barrier","time": 8018,"x": 0.5,"height": 1289},{"type": "dot","time": 8337,"x": 0.4756502118766157,"value": 4},{"type": "dot","time": 8656,"x": 0.7289225983617473,"value": 4},{"type": "dot","time": 8975,"x": 0.43307489916654285,"value": 7},{"type": "dot","time": 9294,"x": 0.631806898264998,"value": 3},{"type": "dot","time": 9613,"x": 0.6246568412007735,"value": 4},{"type": "brick","time": 9932,"x": 0.3333333333333333,"value": 7},{"type": "brick","time": 10251,"x": 0.6666666666666666,"value": 2},{"type": "dot","time": 10570,"x": 0.9316731163465288,"value": 6},{"type": "barrier","time": 10889,"x": 0.75,"height": 2409},{"type": "dot","time": 11208,"x": 0.9331610411383274,"value": 2},{"type": "dot","time": 11527,"x": 0.967383342858116,"value": 6},{"type": "brick","time": 11846,"x": 1.0,"value": 8},{"type": "brick","time": 12165,"x": 1.0,"value": 12},{"type": "dot","time": 12484,"x": 0.1639049184626853,"value": 2},{"type": "brick","time": 12803,"x": 0.3333333333333333,"value": 12},{"type": "dot","time": 13122,"x": 0.6777891785789655,"value": 6},{"type": "brick","time": 13441,"x": 0.6666666666666666,"value": 4},{"type": "dot","time": 13760,"x": 0.2177271937037264,"value": 9},{"type": "brick","time": 14079,"x": 1.0,"value": 20},{"type": "barrier","time": 14398,"x": 0.25,"height": 1511},{"type": "brick","time": 14717,"x": 1.0,"value": 15},{"type": "barrier","time": 15036,"x": 0.5,"height": 1000},{"type": "barrier","time": 15036,"x": 0.75,"height": 1000},{"type": "dot","time": 15136,"x": 0.7866666666666666,"value": 2},{"type": "brick","time": 16036,"x": 0.6666666666666666,"value": 9},{"type": "brick","time": 16355,"x": 0.0,"value": 20},{"type": "brick","time": 16674,"x": 0.6666666666666666,"value": 4},{"type": "brick","time": 16993,"x": 0.0,"value": 16},{"type": "brick","time": 17312,"x": 0.6666666666666666,"value": 11},{"type": "dot","time": 17631,"x": 0.35192053399834133,"value": 8},{"type": "brick","time": 17950,"x": 0.3333333333333333,"value": 5},{"type": "brick","time": 18269,"x": 0.6666666666666666,"value": 10},{"type": "dot","time": 18588,"x": 0.3801509123853528,"value": 8},{"type": "brick","time": 18907,"x": 0.0,"value": 5},{"type": "brick","time": 18907,"x": 0.3333333333333333,"value": 16},{"type": "brick","time": 18907,"x": 0.6666666666666666,"value": 8},{"type": "brick","time": 18907,"x": 1.0,"value": 10},{"type": "brick","time": 19226,"x": 0.0,"value": 5},{"type": "drill","time": 19545,"x": 0.49604233869517733},{"type": "brick","time": 19864,"x": 1.0,"value": 20},{"type": "brick","time": 20183,"x": 0.3333333333333333,"value": 9},{"type": "dot","time": 20502,"x": 0.3653370590245638,"value": 9},{"type": "dot","time": 20821,"x": 0.5814102448774369,"value": 6},{"type": "brick","time": 21140,"x": 0.6666666666666666,"value": 15},{"type": "dot","time": 21459,"x": 0.8347311116578804,"value": 3},{"type": "brick","time": 21778,"x": 1.0,"value": 8},{"type": "brick","time": 22097,"x": 1.0,"value": 3},{"type": "dot","time": 22416,"x": 0.6872451395016097,"value": 9},{"type": "doubleup","time": 22735,"x": 0.10824838846644369},{"type": "doubleup","time": 23054,"x": 0.054074699181707264},{"type": "brick","time": 23373,"x": 0.6666666666666666,"value": 4},{"type": "doubleup","time": 23692,"x": 0.10259693929951386},{"type": "brick","time": 24011,"x": 0.0,"value": 3},{"type": "brick","time": 24011,"x": 0.3333333333333333,"value": 6},{"type": "brick","time": 24011,"x": 0.6666666666666666,"value": 16},{"type": "brick","time": 24011,"x": 1.0,"value": 16},{"type": "brick","time": 24330,"x": 1.0,"value": 15},{"type": "barrier","time": 24649,"x": 0.25,"height": 2874},{"type": "barrier","time": 24968,"x": 0.25,"height": 2434},{"type": "dot","time": 25287,"x": 0.3799621985743502,"value": 3},{"type": "dot","time": 25606,"x": 0.5262065272862526,"value": 5},{"type": "dot","time": 25925,"x": 0.6469872463680945,"value": 7},{"type": "drill","time": 26244,"x": 0.03993837464699568},{"type": "dot","time": 26563,"x": 0.42225251778491246,"value": 1},{"type": "dot","time": 26882,"x": 0.23048129813341922,"value": 3},{"type": "brick","time": 27201,"x": 0.6666666666666666,"value": 1},{"type": "dot","time": 27520,"x": 0.01859758049186988,"value": 4},{"type": "dot","time": 27839,"x": 0.250389811325046,"value": 2},{"type": "brick","time": 28158,"x": 0.0,"value": 20},{"type": "dot","time": 28477,"x": 0.4679508592492947,"value": 2},{"type": "dot","time": 28796,"x": 0.8138453914708705,"value": 7},{"type": "brick","time": 29115,"x": 0.0,"value": 1},{"type": "dot","time": 29434,"x": 0.5631080989460565,"value": 9},{"type": "brick","time": 29753,"x": 0.3333333333333333,"value": 18},{"type": "barrier","time": 30072,"x": 0.5,"height": 1989},{"type": "brick","time": 30391,"x": 0.3333333333333333,"value": 7},{"type": "brick","time": 30710,"x": 0.6666666666666666,"value": 20},{"type": "barrier","time": 31029,"x": 0.75,"height": 2909},{"type": "dot","time": 31348,"x": 0.02416589816218795,"value": 2},{"type": "drill","time": 31667,"x": 0.05179104627229891},{"type": "brick","time": 31986,"x": 0.3333333333333333,"value": 16},{"type": "dot","time": 32305,"x": 0.940764237167672,"value": 7},{"type": "barrier","time": 32624,"x": 0.75,"height": 394},{"type": "dot","time": 32943,"x": 0.8073968671447506,"value": 9},{"type": "barrier","time": 33262,"x": 0.25,"height": 2151},{"type": "barrier","time": 33581,"x": 0.25,"height": 2101},{"type": "brick","time": 33900,"x": 0.3333333333333333,"value": 9},{"type": "brick","time": 34219,"x": 0.6666666666666666,"value": 19},{"type": "dot","time": 34538,"x": 0.6420572245724343,"value": 1},{"type": "brick","time": 34857,"x": 1.0,"value": 15},{"type": "dot","time": 35176,"x": 0.26413045443571304,"value": 2},{"type": "brick","time": 35495,"x": 0.3333333333333333,"value": 18},{"type": "brick","time": 35814,"x": 0.6666666666666666,"value": 20},{"type": "brick","time": 36133,"x": 0.0,"value": 20},{"type": "brick","time": 36133,"x": 0.3333333333333333,"value": 15},{"type": "brick","time": 36133,"x": 0.6666666666666666,"value": 18},{"type": "brick","time": 36133,"x": 1.0,"value": 13},{"type": "dot","time": 36452,"x": 0.786118756026401,"value": 3},{"type": "dot","time": 36771,"x": 0.7286572962306523,"value": 8},{"type": "brick","time": 37090,"x": 0.3333333333333333,"value": 7},{"type": "dot","time": 37409,"x": 0.006770120631776844,"value": 3},{"type": "brick","time": 37728,"x": 0.0,"value": 6},{"type": "brick","time": 38047,"x": 1.0,"value": 15},{"type": "brick","time": 38366,"x": 0.0,"value": 12},{"type": "dot","time": 38685,"x": 0.5331135701264933,"value": 5},{"type": "brick","time": 39004,"x": 0.6666666666666666,"value": 10},{"type": "barrier","time": 39323,"x": 0.25,"height": 2763},{"type": "dot","time": 39642,"x": 0.3301285564128922,"value": 4},{"type": "brick","time": 39961,"x": 0.0,"value": 2},{"type": "barrier","time": 40280,"x": 0.75,"height": 2093},{"type": "slowdown","time": 40599,"x": 0.660938101679363},{"type": "brick","time": 40918,"x": 0.0,"value": 2},{"type": "brick","time": 41237,"x": 0.3333333333333333,"value": 16},{"type": "dot","time": 41556,"x": 0.7930335876366581,"value": 6},{"type": "brick","time": 41875,"x": 0.3333333333333333,"value": 3},{"type": "doubleup","time": 42194,"x": 0.3207004250954001},{"type": "barrier","time": 42513,"x": 0.75,"height": 860},{"type": "dot","time": 42832,"x": 0.781035274341455,"value": 5},{"type": "barrier","time": 43151,"x": 0.0,"height": 1000},{"type": "barrier","time": 43151,"x": 0.25,"height": 1000},{"type": "dot","time": 43251,"x": 0.12,"value": 8},{"type": "brick","time": 44151,"x": 0.0,"value": 1},{"type": "dot","time": 44470,"x": 0.7316378823411457,"value": 3},{"type": "barrier","time": 44789,"x": 0.25,"height": 868},{"type": "brick","time": 45108,"x": 0.6666666666666666,"value": 19},{"type": "slowdown","time": 45427,"x": 0.49480124688308014},{"type": "brick","time": 45746,"x": 0.6666666666666666,"value": 6},{"type": "brick","time": 46065,"x": 0.6666666666666666,"value": 15},{"type": "dot","time": 46384,"x": 0.4781242727009172,"value": 5},{"type": "barrier","time": 46703,"x": 0.5,"height": 1486},{"type": "brick","time": 47022,"x": 0.0,"value": 11},{"type": "dot","time": 47341,"x": 0.2795589943795316,"value": 1},{"type": "barrier","time": 47660,"x": 0.75,"height": 981},{"type": "barrier","time": 47979,"x": 0.25,"height": 2967},{"type": "brick","time": 48298,"x": 1.0,"value": 19},{"type": "barrier","time": 48617,"x": 0.25,"height": 993},{"type": "dot","time": 48936,"x": 0.4389097862057869,"value": 9},{"type": "brick","time": 49255,"x": 0.3333333333333333,"value": 4},{"type": "brick","time": 49574,"x": 1.0,"value": 16},{"type": "dot","time": 49893,"x": 0.726480016265908,"value": 3},{"type": "barrier","time": 50212,"x": 0.75,"height": 1000},{"type": "barrier","time": 50212,"x": 1.0,"height": 1000},{"type": "dot","time": 50312,"x": 1.12,"value": 5},{"type": "brick","time": 51212,"x": 1.0,"value": 4},{"type": "dot","time": 51531,"x": 0.06314387523158616,"value": 6},{"type": "dot","time": 51850,"x": 0.7668862558098202,"value": 1},{"type": "dot","time": 52169,"x": 0.6201853920197319,"value": 5},{"type": "brick","time": 52488,"x": 0.0,"value": 14},{"type": "barrier","time": 52807,"x": 0.75,"height": 1388},{"type": "dot","time": 53126,"x": 0.7759411507497476,"value": 8},{"type": "brick","time": 53445,"x": 0.0,"value": 6},{"type": "brick","time": 53764,"x": 0.3333333333333333,"value": 15},{"type": "barrier","time": 54083,"x": 0.25,"height": 1807},{"type": "dot","time": 54402,"x": 0.9859224136726047,"value": 1},{"type": "dot","time": 54721,"x": 0.3866745742580283,"value": 1},{"type": "brick","time": 55040,"x": 0.6666666666666666,"value": 19},{"type": "brick","time": 55359,"x": 0.0,"value": 15},{"type": "dot","time": 55678,"x": 0.5031278488788176,"value": 9},{"type": "brick","time": 55997,"x": 0.3333333333333333,"value": 7},{"type": "brick","time": 56316,"x": 1.0,"value": 15},{"type": "brick","time": 56635,"x": 0.0,"value": 17},{"type": "brick","time": 56954,"x": 0.0,"value": 7},{"type": "brick","time": 56954,"x": 0.3333333333333333,"value": 12},{"type": "brick","time": 56954,"x": 0.6666666666666666,"value": 6},{"type": "brick","time": 56954,"x": 1.0,"value": 4},{"type": "dot","time": 57273,"x": 0.7486648976979153,"value": 1},{"type": "brick","time": 57592,"x": 0.0,"value": 12},{"type": "brick","time": 57752,"x": 0.3333333333333333,"value": 17},{"type": "brick","time": 57912,"x": 0.6666666666666666,"value": 14},{"type": "brick","time": 58231,"x": 1.0,"value": 11},{"type": "brick","time": 58550,"x": 1.0,"value": 9},{"type": "barrier","time": 58869,"x": 0.75,"height": 1000},{"type": "barrier","time": 58869,"x": 1.0,"height": 1000},{"type": "dot","time": 58969,"x": 1.12,"value": 2},{"type": "brick","time": 59869,"x": 1.0,"value": 11},{"type": "brick","time": 60188,"x": 0.3333333333333333,"value": 7},{"type": "brick","time": 60507,"x": 0.6666666666666666,"value": 3},{"type": "brick","time": 60826,"x": 0.6666666666666666,"value": 1},{"type": "barrier","time": 61145,"x": 0.5,"height": 2539},{"type": "brick","time": 61464,"x": 0.0,"value": 14},{"type": "barrier","time": 61783,"x": 0.5,"height": 1000},{"type": "barrier","time": 61783,"x": 0.75,"height": 1000},{"type": "dot","time": 61883,"x": 0.7866666666666666,"value": 7},{"type": "brick","time": 62783,"x": 0.6666666666666666,"value": 3},{"type": "dot","time": 63102,"x": 0.10931121597999971,"value": 4},{"type": "barrier","time": 63421,"x": 0.0,"height": 1000},{"type": "barrier","time": 63421,"x": 0.25,"height": 1000},{"type": "dot","time": 63521,"x": 0.12,"value": 8},{"type": "brick","time": 64421,"x": 0.0,"value": 1},{"type": "dot","time": 64740,"x": 0.5595636596372787,"value": 4},{"type": "dot","time": 65059,"x": 0.5765229780098279,"value": 5},{"type": "brick","time": 65378,"x": 0.3333333333333333,"value": 13},{"type": "doubleup","time": 65697,"x": 0.4724774326558705},{"type": "dot","time": 66016,"x": 0.7415691517643878,"value": 5},{"type": "brick","time": 66335,"x": 0.3333333333333333,"value": 11},{"type": "barrier","time": 66654,"x": 0.25,"height": 1933},{"type": "brick","time": 66973,"x": 0.3333333333333333,"value": 11},{"type": "dot","time": 67292,"x": 0.21732014426181723,"value": 9},{"type": "dot","time": 67611,"x": 0.6415402568411648,"value": 4},{"type": "barrier","time": 67930,"x": 0.75,"height": 2144},{"type": "brick","time": 68249,"x": 0.0,"value": 15},{"type": "dot","time": 68568,"x": 0.14024819573832603,"value": 6},{"type": "dot","time": 68887,"x": 0.020309191811284655,"value": 3},{"type": "dot","time": 69206,"x": 0.28595052229302986,"value": 4},{"type": "dot","time": 69525,"x": 0.8682908656169218,"value": 3},{"type": "slowdown","time": 69844,"x": 0.4592407869216446},{"type": "dot","time": 70163,"x": 0.9268049296165777,"value": 9},{"type": "dot","time": 70482,"x": 0.9600854603453008,"value": 1},{"type": "dot","time": 70801,"x": 0.8176212200560066,"value": 8},{"type": "barrier","time": 71120,"x": 0.75,"height": 2482},{"type": "dot","time": 71439,"x": 0.5494502635003217,"value": 4},{"type": "brick","time": 71758,"x": 1.0,"value": 15},{"type": "barrier","time": 72077,"x": 0.25,"height": 2912},{"type": "brick","time": 72396,"x": 0.3333333333333333,"value": 5},{"type": "brick","time": 72715,"x": 0.0,"value": 20},{"type": "brick","time": 72875,"x": 0.3333333333333333,"value": 7},{"type": "brick","time": 73035,"x": 0.6666666666666666,"value": 16},{"type": "dot","time": 73354,"x": 0.8745809663996462,"value": 8},{"type": "brick","time": 73673,"x": 1.0,"value": 11},{"type": "drill","time": 73992,"x": 0.4801316840084924},{"type": "brick","time": 74311,"x": 0.3333333333333333,"value": 12},{"type": "dot","time": 74630,"x": 0.8336364390150599,"value": 7},{"type": "brick","time": 74949,"x": 0.3333333333333333,"value": 10},{"type": "brick","time": 75268,"x": 0.0,"value": 4},{"type": "barrier","time": 75587,"x": 0.75,"height": 2261},{"type": "brick","time": 75906,"x": 1.0,"value": 15},{"type": "brick","time": 76225,"x": 0.3333333333333333,"value": 9},{"type": "brick","time": 76544,"x": 0.0,"value": 1},{"type": "dot","time": 76863,"x": 0.48532929788305856,"value": 8},{"type": "barrier","time": 77182,"x": 0.75,"height": 1742},{"type": "dot","time": 77501,"x": 0.9640207418087381,"value": 7},{"type": "dot","time": 77820,"x": 0.8058053469921872,"value": 6},{"type": "brick","time": 78139,"x": 0.0,"value": 11},{"type": "dot","time": 78458,"x": 0.6966224240522743,"value": 8},{"type": "dot","time": 78777,"x": 0.26168822492123567,"value": 4},{"type": "dot","time": 79096,"x": 0.31717937042043487,"value": 7},{"type": "dot","time": 79415,"x": 0.791581569362471,"value": 9},{"type": "dot","time": 79734,"x": 0.968657299279302,"value": 8},{"type": "brick","time": 80053,"x": 0.0,"value": 14},{"type": "brick","time": 80053,"x": 0.3333333333333333,"value": 18},{"type": "brick","time": 80053,"x": 0.6666666666666666,"value": 20},{"type": "brick","time": 80053,"x": 1.0,"value": 9}]}