{"params": {"level": 103,"timelimit": 56490,"initialscore": 11,"targetscore": 43,"lanespeed": 0.7941020041846683,"instructions": null},"entities": [{"type": "dot","time": 1000,"x": 0.5883001771552611,"value": 3},{"type": "barrier","time": 1300,"x": 0.48089010791134235,"height": 1357},{"type": "brick","time": 1600,"x": 0.04424087356131168,"value": 18},{"type": "brick","time": 1900,"x": 0.16325247801187814,"value": 16},{"type": "brick","time": 2200,"x": 0.3061799649715339,"value": 8},{"type": "barrier","time": 2500,"x": 0.5786961207924023,"height": 670},{"type": "barrier","time": 2800,"x": 0.11238232589199837,"height": 2706},{"type": "dot","time": 3100,"x": 0.49305135834020053,"value": 1},{"type": "brick","time": 3400,"x": 0.5003283593915536,"value": 14},{"type": "dot","time": 3700,"x": 0.8856174038170731,"value": 7},{"type": "brick","time": 4000,"x": 0.3299335446581869,"value": 15},{"type": "brick","time": 4300,"x": 0.3661982199346059,"value": 8},{"type": "brick","time": 4600,"x": 0.5406501326872193,"value": 1},{"type": "barrier","time": 4900,"x": 0.8651509927505814,"height": 2158},{"type": "brick","time": 5200,"x": 0.8356063047902147,"value": 11},{"type": "barrier","time": 5500,"x": 0.1764608554475503,"height": 2682},{"type": "doubleup","time": 5800,"x": 0.9045519749920027},{"type": "drill","time": 6100,"x": 0.9816538378244688},{"type": "dot","time": 6400,"x": 0.24997190754308019,"value": 7},{"type": "brick","time": 6700,"x": 0.10035467215228122,"value": 14},{"type": "brick","time": 7000,"x": 0.8616030802326713,"value": 15},{"type": "barrier","time": 7300,"x": 0.8951526391188138,"height": 1981},{"type": "barrier","time": 7600,"x": 0.09443010776477567,"height": 1658},{"type": "dot","time": 7900,"x": 0.04725234175807169,"value": 5},{"type": "brick","time": 8200,"x": 0.7817226417943002,"value": 9},{"type": "dot","time": 8500,"x": 0.10827202266644642,"value": 6},{"type": "brick","time": 8800,"x": 0.567667262652613,"value": 6},{"type": "dot","time": 9100,"x": 0.2880798111358519,"value": 7},{"type": "brick","time": 9400,"x": 0.8562499826840666,"value": 1},{"type": "brick","time": 9700,"x": 0.45439670363131524,"value": 7},{"type": "brick","time": 10000,"x": 0.8089001524931707,"value": 10},{"type": "dot","time": 10300,"x": 0.31120883392757637,"value": 9},{"type": "brick","time": 10600,"x": 0.7609120466257693,"value": 2},{"type": "dot","time": 10900,"x": 0.3272438282822818,"value": 4},{"type": "brick","time": 11200,"x": 0.7468220248216637,"value": 2},{"type": "dot","time": 11500,"x": 0.41356258447072014,"value": 1},{"type": "dot","time": 11800,"x": 0.243980842664009,"value": 2},{"type": "brick","time": 12100,"x": 0.3951252702873991,"value": 20},{"type": "brick","time": 12400,"x": 0.5655229425183247,"value": 8},{"type": "dot","time": 12700,"x": 0.2547714800524883,"value": 2},{"type": "dot","time": 13000,"x": 0.47699022826718007,"value": 8},{"type": "brick","time": 13300,"x": 0.5798476194369213,"value": 17},{"type": "brick","time": 13600,"x": 0.46213546450491694,"value": 16},{"type": "brick","time": 13900,"x": 0.25278479632609074,"value": 16},{"type": "barrier","time": 14200,"x": 0.4457644260257081,"height": 2696},{"type": "drill","time": 14500,"x": 0.8085579578122895},{"type": "brick","time": 14800,"x": 0.47912170135007015,"value": 2},{"type": "brick","time": 15100,"x": 0.04894826657392859,"value": 5},{"type": "barrier","time": 15400,"x": 0.5627426540856362,"height": 1127},{"type": "brick","time": 15700,"x": 0.1448184789226874,"value": 17},{"type": "brick","time": 16000,"x": 0.07744160450304083,"value": 8},{"type": "dot","time": 16300,"x": 0.7919065115581367,"value": 5},{"type": "dot","time": 16600,"x": 0.6371941087887987,"value": 3},{"type": "dot","time": 16900,"x": 0.8865584562044884,"value": 2},{"type": "brick","time": 17200,"x": 0.43093732721940037,"value": 19},{"type": "brick","time": 17500,"x": 0.7612260300548354,"value": 12},{"type": "brick","time": 17800,"x": 0.8195647835686244,"value": 1},{"type": "brick","time": 18100,"x": 0.5943860778884538,"value": 7},{"type": "brick","time": 18400,"x": 0.2722848309119875,"value": 12},{"type": "brick","time": 18700,"x": 0.39369150375861073,"value": 6},{"type": "barrier","time": 19000,"x": 0.31637006999091455,"height": 2364},{"type": "barrier","time": 19300,"x": 0.7571554264279478,"height": 2550},{"type": "dot","time": 19600,"x": 0.7976943233753248,"value": 6},{"type": "brick","time": 19900,"x": 0.47050396673400463,"value": 18},{"type": "brick","time": 20200,"x": 0.18849213441196921,"value": 20},{"type": "barrier","time": 20500,"x": 0.006102368722978979,"height": 1272},{"type": "dot","time": 20800,"x": 0.20089799429686717,"value": 1},{"type": "brick","time": 21100,"x": 0.7282921280130182,"value": 20},{"type": "dot","time": 21400,"x": 0.707508628130237,"value": 9},{"type": "brick","time": 21700,"x": 0.6766937994541281,"value": 5},{"type": "brick","time": 22000,"x": 0.6115458917386066,"value": 10},{"type": "barrier","time": 22300,"x": 0.4954299121311255,"height": 1206},{"type": "brick","time": 22600,"x": 0.25338645790631054,"value": 1},{"type": "dot","time": 22900,"x": 0.9950757250364455,"value": 1},{"type": "brick","time": 23200,"x": 0.5500444582159636,"value": 5},{"type": "brick","time": 23500,"x": 0.9949617291201679,"value": 2},{"type": "dot","time": 23800,"x": 0.3059425197912765,"value": 5},{"type": "dot","time": 24100,"x": 0.22762512502457377,"value": 5},{"type": "brick","time": 24400,"x": 0.011551035948132338,"value": 6},{"type": "dot","time": 24700,"x": 0.39019204051300715,"value": 8},{"type": "brick","time": 25000,"x": 0.03259217170603057,"value": 13},{"type": "dot","time": 25300,"x": 0.12904672547168716,"value": 8},{"type": "barrier","time": 25600,"x": 0.5393354628245831,"height": 2497},{"type": "barrier","time": 25900,"x": 0.4903407432893335,"height": 1700},{"type": "dot","time": 26200,"x": 0.18604053083370864,"value": 2},{"type": "dot","time": 26500,"x": 0.9563111208272922,"value": 1},{"type": "barrier","time": 26800,"x": 0.0851605104083627,"height": 1001},{"type": "brick","time": 27100,"x": 0.8255693322772076,"value": 10},{"type": "brick","time": 27400,"x": 0.06554423747760729,"value": 7},{"type": "brick","time": 27700,"x": 0.2811406470594173,"value": 11},{"type": "dot","time": 28000,"x": 0.05733973637132839,"value": 9},{"type": "slowdown","time": 28300,"x": 0.02292252917341908},{"type": "dot","time": 28600,"x": 0.3791773047963759,"value": 9},{"type": "dot","time": 28900,"x": 0.6271599563335795,"value": 2},{"type": "dot","time": 29200,"x": 0.6096393530969216,"value": 3},{"type": "dot","time": 29500,"x": 0.9524140938173372,"value": 4},{"type": "dot","time": 29800,"x": 0.9732478538025948,"value": 8},{"type": "brick","time": 30100,"x": 0.6564277240428431,"value": 4},{"type": "dot","time": 30400,"x": 0.39515715683756525,"value": 8},{"type": "dot","time": 30700,"x": 0.6965078856889662,"value": 8},{"type": "dot","time": 31000,"x": 0.7535977519177514,"value": 4},{"type": "dot","time": 31300,"x": 0.048067646606856806,"value": 2},{"type": "dot","time": 31600,"x": 0.3292876888954086,"value": 6},{"type": "brick","time": 31900,"x": 0.04117561871643227,"value": 5},{"type": "brick","time": 32200,"x": 0.14288896543393093,"value": 8},{"type": "dot","time": 32500,"x": 0.903410769809151,"value": 8},{"type": "dot","time": 32800,"x": 0.18741817395065485,"value": 2},{"type": "brick","time": 33100,"x": 0.34997514138959995,"value": 17},{"type": "dot","time": 33400,"x": 0.6280774961426009,"value": 6},{"type": "brick","time": 33700,"x": 0.7790457639296534,"value": 8},{"type": "dot","time": 34000,"x": 0.34319688196786313,"value": 2},{"type": "brick","time": 34300,"x": 0.6638158300634964,"value": 17},{"type": "brick","time": 34600,"x": 0.42644765773785853,"value": 2},{"type": "dot","time": 34900,"x": 0.6045058138586752,"value": 9},{"type": "dot","time": 35200,"x": 0.9947438698104268,"value": 6},{"type": "brick","time": 35500,"x": 0.8281226909640745,"value": 18},{"type": "dot","time": 35800,"x": 0.7287645019827288,"value": 6},{"type": "barrier","time": 36100,"x": 0.4403768449223967,"height": 765},{"type": "brick","time": 36400,"x": 0.45306573301513575,"value": 11},{"type": "dot","time": 36700,"x": 0.11812900087297729,"value": 5},{"type": "drill","time": 37000,"x": 0.061998022692632215},{"type": "barrier","time": 37300,"x": 0.21205669348085832,"height": 2502},{"type": "brick","time": 37600,"x": 0.30447321464231936,"value": 18},{"type": "dot","time": 37900,"x": 0.1163528977173397,"value": 2},{"type": "brick","time": 38200,"x": 0.3708027335016558,"value": 12},{"type": "brick","time": 38500,"x": 0.34256368032152895,"value": 18},{"type": "brick","time": 38800,"x": 0.8459685528192725,"value": 5},{"type": "brick","time": 39100,"x": 0.24541303316594898,"value": 1},{"type": "brick","time": 39400,"x": 0.2145042241440246,"value": 17},{"type": "brick","time": 39700,"x": 0.4871735339451313,"value": 17},{"type": "brick","time": 40000,"x": 0.8646982424586945,"value": 13},{"type": "dot","time": 40300,"x": 0.8359689230349644,"value": 7},{"type": "brick","time": 40600,"x": 0.3426728323316628,"value": 16},{"type": "brick","time": 40900,"x": 0.002291149521484126,"value": 2},{"type": "dot","time": 41200,"x": 0.00020495661527020204,"value": 2},{"type": "brick","time": 41500,"x": 0.12361187879220192,"value": 18},{"type": "brick","time": 41800,"x": 0.6098018600411833,"value": 14},{"type": "brick","time": 42100,"x": 0.42666775530160783,"value": 18},{"type": "dot","time": 42400,"x": 0.7846403286822446,"value": 6},{"type": "brick","time": 42700,"x": 0.9961957172967771,"value": 5},{"type": "brick","time": 43000,"x": 0.31352993340091784,"value": 3},{"type": "brick","time": 43300,"x": 0.1758476276401607,"value": 1},{"type": "barrier","time": 43600,"x": 0.35807919829112533,"height": 1245},{"type": "brick","time": 43900,"x": 0.7252809896393105,"value": 17},{"type": "brick","time": 44200,"x": 0.18727089356233284,"value": 5},{"type": "dot","time": 44500,"x": 0.6664111628423742,"value": 5},{"type": "dot","time": 44800,"x": 0.22647878545909894,"value": 5},{"type": "dot","time": 45100,"x": 0.27125238730464285,"value": 8},{"type": "dot","time": 45400,"x": 0.5141279444881507,"value": 6},{"type": "brick","time": 45700,"x": 0.7922357274798626,"value": 7},{"type": "brick","time": 46000,"x": 0.5675476938637342,"value": 10},{"type": "barrier","time": 46300,"x": 0.9943415910272106,"height": 1019},{"type": "brick","time": 46600,"x": 0.20997211793314108,"value": 6},{"type": "brick","time": 46900,"x": 0.554924224608548,"value": 3},{"type": "brick","time": 47200,"x": 0.8844224956890199,"value": 13},{"type": "brick","time": 47500,"x": 0.13963240257622989,"value": 16},{"type": "dot","time": 47800,"x": 0.9703787989411601,"value": 6},{"type": "brick","time": 48100,"x": 0.9236527223193894,"value": 6},{"type": "brick","time": 48400,"x": 0.12013363990851367,"value": 4},{"type": "dot","time": 48700,"x": 0.8324284458936558,"value": 3},{"type": "dot","time": 49000,"x": 0.9167637415689263,"value": 1},{"type": "barrier","time": 49300,"x": 0.8078936816210147,"height": 2290},{"type": "dot","time": 49600,"x": 0.31781284416353606,"value": 1},{"type": "brick","time": 49900,"x": 0.45845109646677973,"value": 7},{"type": "brick","time": 50200,"x": 0.5750440928681491,"value": 2},{"type": "brick","time": 50500,"x": 0.19122327318882404,"value": 13},{"type": "brick","time": 50800,"x": 0.8130291451389147,"value": 17},{"type": "brick","time": 51100,"x": 0.4021069117087336,"value": 3},{"type": "brick","time": 51400,"x": 0.21456001031048355,"value": 8},{"type": "brick","time": 51700,"x": 0.9045701716930599,"value": 16},{"type": "dot","time": 52000,"x": 0.7576579644345415,"value": 1},{"type": "barrier","time": 52300,"x": 0.06317038652833096,"height": 1083},{"type": "dot","time": 52600,"x": 0.524564364490504,"value": 2},{"type": "barrier","time": 52900,"x": 0.895775329783904,"height": 1837},{"type": "dot","time": 53200,"x": 0.09988878791674494,"value": 7},{"type": "brick","time": 53500,"x": 0.24767869705401524,"value": 16},{"type": "brick","time": 53800,"x": 0.07136992585886881,"value": 11},{"type": "brick","time": 54100,"x": 0.05158254127098505,"value": 19},{"type": "dot","time": 54400,"x": 0.3536580951468181,"value": 9},{"type": "barrier","time": 54700,"x": 0.28483589446797786,"height": 555},{"type": "dot","time": 55000,"x": 0.9079464966719437,"value": 9},{"type": "dot","time": 55300,"x": 0.27747784389923524,"value": 3},{"type": "dot","time": 55600,"x": 0.17450409065469963,"value": 3},{"type": "brick","time": 55900,"x": 0.9255500212016311,"value": 9},{"type": "dot","time": 56200,"x": 0.6711925334941081,"value": 9},{"type": "brick","time": 56500,"x": 0.051790762958977776,"value": 7},{"type": "brick","time": 56800,"x": 0.683484202729909,"value": 6},{"type": "barrier","time": 57100,"x": 0.5329413057104423,"height": 878}]}