{"params": {"level": 284,"timelimit": 58692,"initialscore": 11,"targetscore": 45,"lanespeed": 1.0890855489784064},"entities": [{"type": "brick","time": 1000,"x": 0.3333333333333333,"value": 6},{"type": "dot","time": 1183,"x": 0.9499741608330966,"value": 9},{"type": "brick","time": 1366,"x": 0.3333333333333333,"value": 4},{"type": "dot","time": 1549,"x": 0.3222312127989675,"value": 7},{"type": "brick","time": 1732,"x": 0.0,"value": 12},{"type": "barrier","time": 1915,"x": 0.5,"height": 1584},{"type": "brick","time": 2098,"x": 0.3333333333333333,"value": 7},{"type": "brick","time": 2281,"x": 1.0,"value": 13},{"type": "brick","time": 2464,"x": 0.0,"value": 11},{"type": "brick","time": 2647,"x": 1.0,"value": 7},{"type": "dot","time": 2830,"x": 0.19544021079072116,"value": 7},{"type": "barrier","time": 3013,"x": 0.25,"height": 2407},{"type": "dot","time": 3196,"x": 0.9078103122788783,"value": 2},{"type": "dot","time": 3379,"x": 0.34722485064503417,"value": 3},{"type": "brick","time": 3562,"x": 0.3333333333333333,"value": 11},{"type": "brick","time": 3745,"x": 0.3333333333333333,"value": 13},{"type": "slowdown","time": 3928,"x": 0.11825614574716892},{"type": "barrier","time": 4111,"x": 0.5,"height": 2567},{"type": "slowdown","time": 4294,"x": 0.96018819370352},{"type": "brick","time": 4477,"x": 0.0,"value": 20},{"type": "brick","time": 4477,"x": 0.3333333333333333,"value": 5},{"type": "brick","time": 4477,"x": 0.6666666666666666,"value": 20},{"type": "brick","time": 4477,"x": 1.0,"value": 17},{"type": "slowdown","time": 4660,"x": 0.029210384932891298},{"type": "dot","time": 4843,"x": 0.6039877575009652,"value": 7},{"type": "dot","time": 5026,"x": 0.5973190112050053,"value": 4},{"type": "brick","time": 5209,"x": 0.0,"value": 16},{"type": "brick","time": 5369,"x": 0.3333333333333333,"value": 3},{"type": "brick","time": 5529,"x": 0.6666666666666666,"value": 9},{"type": "brick","time": 5712,"x": 1.0,"value": 19},{"type": "brick","time": 5872,"x": 0.6666666666666666,"value": 8},{"type": "brick","time": 6032,"x": 0.3333333333333333,"value": 16},{"type": "brick","time": 6215,"x": 0.3333333333333333,"value": 11},{"type": "dot","time": 6398,"x": 0.6066100873143514,"value": 8},{"type": "dot","time": 6581,"x": 0.3917627664728386,"value": 5},{"type": "barrier","time": 6764,"x": 0.0,"height": 1000},{"type": "barrier","time": 6764,"x": 0.25,"height": 1000},{"type": "dot","time": 6864,"x": 0.12,"value": 2},{"type": "brick","time": 7764,"x": 0.0,"value": 14},{"type": "brick","time": 7947,"x": 0.0,"value": 2},{"type": "brick","time": 8130,"x": 1.0,"value": 5},{"type": "barrier","time": 8313,"x": 0.75,"height": 1000},{"type": "barrier","time": 8313,"x": 1.0,"height": 1000},{"type": "dot","time": 8413,"x": 1.12,"value": 9},{"type": "brick","time": 9313,"x": 1.0,"value": 18},{"type": "dot","time": 9496,"x": 0.8994498475229306,"value": 5},{"type": "brick","time": 9679,"x": 1.0,"value": 10},{"type": "barrier","time": 9862,"x": 0.25,"height": 1682},{"type": "brick","time": 10045,"x": 0.6666666666666666,"value": 8},{"type": "barrier","time": 10228,"x": 0.25,"height": 2890},{"type": "barrier","time": 10411,"x": 0.25,"height": 561},{"type": "brick","time": 10594,"x": 0.3333333333333333,"value": 2},{"type": "brick","time": 10777,"x": 0.0,"value": 14},{"type": "drill","time": 10960,"x": 0.6320529353889826},{"type": "barrier","time": 11143,"x": 0.75,"height": 342},{"type": "dot","time": 11326,"x": 0.8473255487774711,"value": 5},{"type": "slowdown","time": 11509,"x": 0.8160292621377762},{"type": "dot","time": 11692,"x": 0.5987099439488909,"value": 7},{"type": "dot","time": 11875,"x": 0.48079572575967844,"value": 9},{"type": "dot","time": 12058,"x": 0.007989369367170096,"value": 6},{"type": "brick","time": 12241,"x": 0.6666666666666666,"value": 6},{"type": "slowdown","time": 12424,"x": 0.04314824644739346},{"type": "brick","time": 12607,"x": 0.0,"value": 7},{"type": "barrier","time": 12790,"x": 0.25,"height": 997},{"type": "dot","time": 12973,"x": 0.3168521271702476,"value": 9},{"type": "brick","time": 13156,"x": 0.6666666666666666,"value": 17},{"type": "dot","time": 13339,"x": 0.3220255483051082,"value": 5},{"type": "dot","time": 13522,"x": 0.29561414140774867,"value": 7},{"type": "brick","time": 13705,"x": 0.0,"value": 8},{"type": "brick","time": 13865,"x": 0.3333333333333333,"value": 4},{"type": "brick","time": 14025,"x": 0.6666666666666666,"value": 5},{"type": "brick","time": 14208,"x": 1.0,"value": 9},{"type": "dot","time": 14391,"x": 0.22210949855016549,"value": 3},{"type": "dot","time": 14574,"x": 0.8516501239403699,"value": 2},{"type": "brick","time": 14757,"x": 0.0,"value": 14},{"type": "brick","time": 14940,"x": 0.0,"value": 13},{"type": "dot","time": 15123,"x": 0.3651185343251594,"value": 7},{"type": "dot","time": 15306,"x": 0.051785943739470985,"value": 1},{"type": "brick","time": 15489,"x": 0.6666666666666666,"value": 7},{"type": "dot","time": 15672,"x": 0.9397511638257219,"value": 9},{"type": "dot","time": 15855,"x": 0.8610345346407368,"value": 5},{"type": "dot","time": 16038,"x": 0.13320015905705074,"value": 8},{"type": "brick","time": 16221,"x": 0.3333333333333333,"value": 12},{"type": "barrier","time": 16404,"x": 0.75,"height": 1356},{"type": "dot","time": 16587,"x": 0.8495564713713766,"value": 8},{"type": "brick","time": 16770,"x": 0.3333333333333333,"value": 12},{"type": "dot","time": 16953,"x": 0.8188285568072471,"value": 8},{"type": "brick","time": 17136,"x": 0.6666666666666666,"value": 10},{"type": "dot","time": 17319,"x": 0.8229251859052903,"value": 3},{"type": "brick","time": 17502,"x": 0.3333333333333333,"value": 20},{"type": "brick","time": 17685,"x": 0.6666666666666666,"value": 1},{"type": "dot","time": 17868,"x": 0.09318527871275573,"value": 6},{"type": "dot","time": 18051,"x": 0.8947543400716723,"value": 6},{"type": "dot","time": 18234,"x": 0.5295763825013031,"value": 8},{"type": "dot","time": 18417,"x": 0.8993867053843569,"value": 5},{"type": "brick","time": 18600,"x": 0.6666666666666666,"value": 1},{"type": "brick","time": 18783,"x": 1.0,"value": 19},{"type": "brick","time": 18943,"x": 0.6666666666666666,"value": 5},{"type": "brick","time": 19103,"x": 0.3333333333333333,"value": 19},{"type": "brick","time": 19286,"x": 0.3333333333333333,"value": 1},{"type": "dot","time": 19469,"x": 0.39306759373480116,"value": 1},{"type": "brick","time": 19652,"x": 0.6666666666666666,"value": 12},{"type": "dot","time": 19835,"x": 0.6451028876104662,"value": 1},{"type": "brick","time": 20018,"x": 0.0,"value": 18},{"type": "brick","time": 20018,"x": 0.3333333333333333,"value": 1},{"type": "brick","time": 20018,"x": 0.6666666666666666,"value": 19},{"type": "brick","time": 20018,"x": 1.0,"value": 1},{"type": "brick","time": 20201,"x": 0.0,"value": 14},{"type": "dot","time": 20384,"x": 0.31340328155863606,"value": 1},{"type": "dot","time": 20567,"x": 0.04768217303034217,"value": 1},{"type": "brick","time": 20750,"x": 1.0,"value": 4},{"type": "dot","time": 20933,"x": 0.5543043181401827,"value": 7},{"type": "dot","time": 21116,"x": 0.7668089769396181,"value": 3},{"type": "brick","time": 21299,"x": 0.3333333333333333,"value": 3},{"type": "brick","time": 21482,"x": 1.0,"value": 5},{"type": "brick","time": 21665,"x": 1.0,"value": 15},{"type": "brick","time": 21825,"x": 0.6666666666666666,"value": 14},{"type": "brick","time": 21985,"x": 0.3333333333333333,"value": 11},{"type": "slowdown","time": 22168,"x": 0.28931241502216676},{"type": "brick","time": 22351,"x": 0.0,"value": 15},{"type": "brick","time": 22511,"x": 0.3333333333333333,"value": 1},{"type": "brick","time": 22671,"x": 0.6666666666666666,"value": 2},{"type": "barrier","time": 22854,"x": 0.5,"height": 489},{"type": "brick","time": 23037,"x": 1.0,"value": 6},{"type": "dot","time": 23220,"x": 0.48951174227294436,"value": 5},{"type": "dot","time": 23403,"x": 0.9756298761291816,"value": 7},{"type": "brick","time": 23586,"x": 0.0,"value": 15},{"type": "brick","time": 23586,"x": 0.3333333333333333,"value": 6},{"type": "brick","time": 23586,"x": 0.6666666666666666,"value": 19},{"type": "brick","time": 23586,"x": 1.0,"value": 16},{"type": "brick","time": 23769,"x": 1.0,"value": 9},{"type": "dot","time": 23952,"x": 0.059735530374875445,"value": 3},{"type": "dot","time": 24135,"x": 0.9517853893030802,"value": 4},{"type": "dot","time": 24318,"x": 0.11225069837054658,"value": 6},{"type": "brick","time": 24501,"x": 0.3333333333333333,"value": 11},{"type": "dot","time": 24684,"x": 0.7790718341099141,"value": 8},{"type": "brick","time": 24867,"x": 0.0,"value": 12},{"type": "dot","time": 25050,"x": 0.8494600104654395,"value": 2},{"type": "dot","time": 25233,"x": 0.5245072965223823,"value": 5},{"type": "dot","time": 25416,"x": 0.9844952228274106,"value": 5},{"type": "dot","time": 25599,"x": 0.26718517412331333,"value": 3},{"type": "brick","time": 25782,"x": 0.6666666666666666,"value": 8},{"type": "dot","time": 25965,"x": 0.8334706298465441,"value": 3},{"type": "brick","time": 26148,"x": 0.6666666666666666,"value": 7},{"type": "dot","time": 26331,"x": 0.9112168733005982,"value": 3},{"type": "brick","time": 26514,"x": 0.0,"value": 2},{"type": "brick","time": 26697,"x": 1.0,"value": 14},{"type": "brick","time": 26880,"x": 0.3333333333333333,"value": 14},{"type": "brick","time": 27063,"x": 0.0,"value": 12},{"type": "dot","time": 27246,"x": 0.6306867341933933,"value": 6},{"type": "brick","time": 27429,"x": 0.0,"value": 14},{"type": "brick","time": 27612,"x": 1.0,"value": 5},{"type": "brick","time": 27795,"x": 0.3333333333333333,"value": 16},{"type": "brick","time": 27978,"x": 0.0,"value": 8},{"type": "brick","time": 27978,"x": 0.3333333333333333,"value": 1},{"type": "brick","time": 27978,"x": 0.6666666666666666,"value": 14},{"type": "brick","time": 27978,"x": 1.0,"value": 11},{"type": "dot","time": 28161,"x": 0.9294693645596054,"value": 1},{"type": "dot","time": 28344,"x": 0.9149380110549616,"value": 1},{"type": "dot","time": 28527,"x": 0.8853017741889982,"value": 3},{"type": "brick","time": 28710,"x": 0.6666666666666666,"value": 8},{"type": "dot","time": 28893,"x": 0.3134698884378818,"value": 4},{"type": "brick","time": 29076,"x": 0.0,"value": 4},{"type": "dot","time": 29259,"x": 0.7997825689996114,"value": 3},{"type": "dot","time": 29442,"x": 0.012363196616611893,"value": 1},{"type": "dot","time": 29625,"x": 0.6798245491641239,"value": 1},{"type": "dot","time": 29808,"x": 0.6585639991406564,"value": 2},{"type": "brick","time": 29991,"x": 0.0,"value": 15},{"type": "dot","time": 30174,"x": 0.024252039274097803,"value": 1},{"type": "dot","time": 30357,"x": 0.6267917952177794,"value": 8},{"type": "dot","time": 30540,"x": 0.5083997676411633,"value": 5},{"type": "brick","time": 30723,"x": 0.0,"value": 7},{"type": "dot","time": 30906,"x": 0.962469768540786,"value": 9},{"type": "brick","time": 31089,"x": 0.0,"value": 6},{"type": "dot","time": 31272,"x": 0.40219243264022064,"value": 9},{"type": "brick","time": 31455,"x": 0.6666666666666666,"value": 1},{"type": "brick","time": 31638,"x": 1.0,"value": 2},{"type": "dot","time": 31821,"x": 0.9167636440392067,"value": 8},{"type": "brick","time": 32004,"x": 0.0,"value": 5},{"type": "brick","time": 32164,"x": 0.3333333333333333,"value": 11},{"type": "brick","time": 32324,"x": 0.6666666666666666,"value": 11},{"type": "dot","time": 32507,"x": 0.8018513651239697,"value": 9},{"type": "dot","time": 32690,"x": 0.8653169621901939,"value": 7},{"type": "barrier","time": 32873,"x": 0.5,"height": 1634},{"type": "brick","time": 33056,"x": 0.0,"value": 6},{"type": "slowdown","time": 33239,"x": 0.46239137038965283},{"type": "brick","time": 33422,"x": 1.0,"value": 15},{"type": "brick","time": 33605,"x": 0.0,"value": 1},{"type": "brick","time": 33605,"x": 0.3333333333333333,"value": 18},{"type": "brick","time": 33605,"x": 0.6666666666666666,"value": 18},{"type": "brick","time": 33605,"x": 1.0,"value": 15},{"type": "dot","time": 33788,"x": 0.6537636786897988,"value": 6},{"type": "dot","time": 33971,"x": 0.6938767106915585,"value": 5},{"type": "dot","time": 34154,"x": 0.5741495889577188,"value": 7},{"type": "dot","time": 34337,"x": 0.46582145673413844,"value": 7},{"type": "drill","time": 34520,"x": 0.5261779313983495},{"type": "dot","time": 34703,"x": 0.41179592976680024,"value": 1},{"type": "dot","time": 34886,"x": 0.6893155080040941,"value": 7},{"type": "barrier","time": 35069,"x": 0.25,"height": 1792},{"type": "brick","time": 35252,"x": 1.0,"value": 10},{"type": "brick","time": 35435,"x": 0.3333333333333333,"value": 7},{"type": "brick","time": 35618,"x": 1.0,"value": 13},{"type": "brick","time": 35801,"x": 0.3333333333333333,"value": 1},{"type": "dot","time": 35984,"x": 0.16524389132371697,"value": 1},{"type": "brick","time": 36167,"x": 0.0,"value": 8},{"type": "dot","time": 36350,"x": 0.567435571961171,"value": 7},{"type": "dot","time": 36533,"x": 0.1964136359231028,"value": 3},{"type": "dot","time": 36716,"x": 0.7219073289084893,"value": 5},{"type": "brick","time": 36899,"x": 1.0,"value": 2},{"type": "brick","time": 37082,"x": 0.3333333333333333,"value": 13},{"type": "brick","time": 37265,"x": 0.0,"value": 7},{"type": "barrier","time": 37448,"x": 0.75,"height": 472},{"type": "dot","time": 37631,"x": 0.537172399368704,"value": 8},{"type": "dot","time": 37814,"x": 0.27603440619331454,"value": 6},{"type": "dot","time": 37997,"x": 0.10113544542409925,"value": 2},{"type": "brick","time": 38180,"x": 0.0,"value": 10},{"type": "dot","time": 38363,"x": 0.2855290826501202,"value": 5},{"type": "barrier","time": 38546,"x": 0.75,"height": 1232},{"type": "slowdown","time": 38729,"x": 0.841820785369471},{"type": "dot","time": 38912,"x": 0.7837681088153372,"value": 8},{"type": "brick","time": 39095,"x": 0.0,"value": 2},{"type": "brick","time": 39278,"x": 1.0,"value": 11},{"type": "barrier","time": 39461,"x": 0.5,"height": 1904},{"type": "barrier","time": 39644,"x": 0.5,"height": 2149},{"type": "brick","time": 39827,"x": 1.0,"value": 10},{"type": "barrier","time": 40010,"x": 0.75,"height": 1000},{"type": "barrier","time": 40010,"x": 1.0,"height": 1000},{"type": "dot","time": 40110,"x": 1.12,"value": 5},{"type": "brick","time": 41010,"x": 1.0,"value": 15},{"type": "brick","time": 41193,"x": 0.0,"value": 18},{"type": "dot","time": 41376,"x": 0.9115678373582358,"value": 4},{"type": "brick","time": 41559,"x": 0.6666666666666666,"value": 5},{"type": "brick","time": 41742,"x": 0.6666666666666666,"value": 2}]}