{"params": {"level": 408,"timelimit": 88487,"initialscore": 13,"targetscore": 48,"lanespeed": 0.7837704198242631},"entities": [{"type": "barrier","time": 1000,"x": 0.25,"height": 1189},{"type": "dot","time": 1255,"x": 0.11680786548701294,"value": 3},{"type": "brick","time": 1510,"x": 1.0,"value": 5},{"type": "dot","time": 1765,"x": 0.7984389503846661,"value": 2},{"type": "brick","time": 2020,"x": 1.0,"value": 16},{"type": "dot","time": 2275,"x": 0.8842650472786664,"value": 5},{"type": "dot","time": 2530,"x": 0.02820710524593495,"value": 8},{"type": "brick","time": 2785,"x": 0.0,"value": 18},{"type": "dot","time": 3040,"x": 0.749804696058793,"value": 5},{"type": "doubleup","time": 3295,"x": 0.26268789008203464},{"type": "dot","time": 3550,"x": 0.9666378136757834,"value": 4},{"type": "brick","time": 3805,"x": 0.0,"value": 3},{"type": "brick","time": 3965,"x": 0.3333333333333333,"value": 20},{"type": "brick","time": 4125,"x": 0.6666666666666666,"value": 2},{"type": "dot","time": 4380,"x": 0.4933453681906932,"value": 8},{"type": "brick","time": 4635,"x": 0.0,"value": 7},{"type": "brick","time": 4635,"x": 0.3333333333333333,"value": 7},{"type": "brick","time": 4635,"x": 0.6666666666666666,"value": 17},{"type": "brick","time": 4635,"x": 1.0,"value": 3},{"type": "dot","time": 4890,"x": 0.14984991243800228,"value": 7},{"type": "barrier","time": 5145,"x": 0.75,"height": 1000},{"type": "barrier","time": 5145,"x": 1.0,"height": 1000},{"type": "dot","time": 5245,"x": 1.12,"value": 7},{"type": "brick","time": 6145,"x": 1.0,"value": 4},{"type": "barrier","time": 6400,"x": 0.75,"height": 943},{"type": "dot","time": 6655,"x": 0.28667136052418785,"value": 4},{"type": "dot","time": 6910,"x": 0.9198413702275573,"value": 8},{"type": "dot","time": 7165,"x": 0.8511708330494148,"value": 7},{"type": "dot","time": 7420,"x": 0.734044952873422,"value": 6},{"type": "barrier","time": 7675,"x": 0.25,"height": 2008},{"type": "brick","time": 7930,"x": 0.6666666666666666,"value": 10},{"type": "doubleup","time": 8185,"x": 0.32913824925502044},{"type": "brick","time": 8440,"x": 1.0,"value": 3},{"type": "dot","time": 8695,"x": 0.6000916661400537,"value": 6},{"type": "dot","time": 8950,"x": 0.938040683901401,"value": 8},{"type": "barrier","time": 9205,"x": 0.25,"height": 1505},{"type": "brick","time": 9460,"x": 0.3333333333333333,"value": 16},{"type": "brick","time": 9715,"x": 0.0,"value": 3},{"type": "brick","time": 9970,"x": 0.0,"value": 1},{"type": "brick","time": 10225,"x": 1.0,"value": 14},{"type": "brick","time": 10480,"x": 0.6666666666666666,"value": 15},{"type": "brick","time": 10735,"x": 0.6666666666666666,"value": 15},{"type": "dot","time": 10990,"x": 0.9925229744225336,"value": 2},{"type": "drill","time": 11245,"x": 0.7568944465086244},{"type": "brick","time": 11500,"x": 0.3333333333333333,"value": 5},{"type": "brick","time": 11755,"x": 1.0,"value": 9},{"type": "brick","time": 11915,"x": 0.6666666666666666,"value": 12},{"type": "brick","time": 12075,"x": 0.3333333333333333,"value": 5},{"type": "dot","time": 12330,"x": 0.17934800486750802,"value": 9},{"type": "dot","time": 12585,"x": 0.1759641164442196,"value": 4},{"type": "brick","time": 12840,"x": 0.0,"value": 1},{"type": "dot","time": 13095,"x": 0.05192767712940283,"value": 7},{"type": "dot","time": 13350,"x": 0.6505337525690887,"value": 5},{"type": "brick","time": 13605,"x": 0.3333333333333333,"value": 20},{"type": "brick","time": 13860,"x": 0.3333333333333333,"value": 18},{"type": "brick","time": 14115,"x": 0.3333333333333333,"value": 17},{"type": "brick","time": 14370,"x": 1.0,"value": 19},{"type": "brick","time": 14625,"x": 1.0,"value": 5},{"type": "dot","time": 14880,"x": 0.3210866179842716,"value": 1},{"type": "dot","time": 15135,"x": 0.18969030544512955,"value": 3},{"type": "brick","time": 15390,"x": 0.0,"value": 7},{"type": "brick","time": 15390,"x": 0.3333333333333333,"value": 18},{"type": "brick","time": 15390,"x": 0.6666666666666666,"value": 11},{"type": "brick","time": 15390,"x": 1.0,"value": 19},{"type": "brick","time": 15645,"x": 0.0,"value": 15},{"type": "brick","time": 15900,"x": 1.0,"value": 3},{"type": "brick","time": 16155,"x": 0.6666666666666666,"value": 12},{"type": "dot","time": 16410,"x": 0.07981510158649352,"value": 9},{"type": "brick","time": 16665,"x": 0.3333333333333333,"value": 4},{"type": "dot","time": 16920,"x": 0.015342406305144385,"value": 3},{"type": "barrier","time": 17175,"x": 0.5,"height": 1074},{"type": "brick","time": 17430,"x": 0.6666666666666666,"value": 12},{"type": "brick","time": 17685,"x": 0.3333333333333333,"value": 3},{"type": "brick","time": 17940,"x": 0.0,"value": 5},{"type": "dot","time": 18195,"x": 0.32116507816303264,"value": 3},{"type": "dot","time": 18450,"x": 0.7344614911222348,"value": 7},{"type": "dot","time": 18705,"x": 0.3845609826191575,"value": 2},{"type": "brick","time": 18960,"x": 0.6666666666666666,"value": 5},{"type": "barrier","time": 19215,"x": 0.75,"height": 1000},{"type": "barrier","time": 19215,"x": 1.0,"height": 1000},{"type": "dot","time": 19315,"x": 1.12,"value": 8},{"type": "brick","time": 20215,"x": 1.0,"value": 13},{"type": "brick","time": 20470,"x": 1.0,"value": 19},{"type": "brick","time": 20725,"x": 0.0,"value": 1},{"type": "dot","time": 20980,"x": 0.14684122157847268,"value": 4},{"type": "brick","time": 21235,"x": 0.6666666666666666,"value": 20},{"type": "barrier","time": 21490,"x": 0.75,"height": 2180},{"type": "dot","time": 21745,"x": 0.7210809515262487,"value": 5},{"type": "dot","time": 22000,"x": 0.7980340077623883,"value": 8},{"type": "barrier","time": 22255,"x": 0.5,"height": 2522},{"type": "slowdown","time": 22510,"x": 0.6224263456393359},{"type": "brick","time": 22765,"x": 0.6666666666666666,"value": 8},{"type": "dot","time": 23020,"x": 0.5627033647738666,"value": 5},{"type": "dot","time": 23275,"x": 0.7329803491157934,"value": 4},{"type": "brick","time": 23530,"x": 0.3333333333333333,"value": 6},{"type": "dot","time": 23785,"x": 0.3818726245694757,"value": 9},{"type": "brick","time": 24040,"x": 0.0,"value": 5},{"type": "slowdown","time": 24295,"x": 0.2998360749571164},{"type": "dot","time": 24550,"x": 0.25445660222907507,"value": 8},{"type": "dot","time": 24805,"x": 0.19869843481676963,"value": 6},{"type": "brick","time": 25060,"x": 0.0,"value": 18},{"type": "brick","time": 25315,"x": 0.6666666666666666,"value": 12},{"type": "brick","time": 25570,"x": 0.3333333333333333,"value": 10},{"type": "slowdown","time": 25825,"x": 0.9854891908606259},{"type": "slowdown","time": 26080,"x": 0.43067235429454265},{"type": "doubleup","time": 26335,"x": 0.46645037644757437},{"type": "dot","time": 26590,"x": 0.8659968403599912,"value": 1},{"type": "dot","time": 26845,"x": 0.09070835396014565,"value": 5},{"type": "dot","time": 27100,"x": 0.45962960271398834,"value": 3},{"type": "dot","time": 27355,"x": 0.08375486853927383,"value": 3},{"type": "brick","time": 27610,"x": 0.3333333333333333,"value": 12},{"type": "barrier","time": 27865,"x": 0.25,"height": 2101},{"type": "brick","time": 28120,"x": 0.3333333333333333,"value": 8},{"type": "brick","time": 28375,"x": 0.6666666666666666,"value": 7},{"type": "dot","time": 28630,"x": 0.6130708912567746,"value": 6},{"type": "dot","time": 28885,"x": 0.06835558259977315,"value": 3},{"type": "drill","time": 29140,"x": 0.4740557616235217},{"type": "brick","time": 29395,"x": 0.0,"value": 19},{"type": "brick","time": 29555,"x": 0.3333333333333333,"value": 8},{"type": "brick","time": 29715,"x": 0.6666666666666666,"value": 3},{"type": "doubleup","time": 29970,"x": 0.2955592759062623},{"type": "dot","time": 30225,"x": 0.89210624753575,"value": 5},{"type": "brick","time": 30480,"x": 0.6666666666666666,"value": 9},{"type": "dot","time": 30735,"x": 0.6476751516560091,"value": 2},{"type": "brick","time": 30990,"x": 0.0,"value": 12},{"type": "dot","time": 31245,"x": 0.27515808480650394,"value": 7},{"type": "brick","time": 31500,"x": 0.3333333333333333,"value": 4},{"type": "brick","time": 31755,"x": 0.6666666666666666,"value": 19},{"type": "slowdown","time": 32010,"x": 0.9706466368214578},{"type": "brick","time": 32265,"x": 0.3333333333333333,"value": 13},{"type": "dot","time": 32520,"x": 0.13329472083894522,"value": 3},{"type": "dot","time": 32775,"x": 0.7717110153837338,"value": 7},{"type": "slowdown","time": 33030,"x": 0.17529280363929511},{"type": "brick","time": 33285,"x": 1.0,"value": 14},{"type": "barrier","time": 33540,"x": 0.75,"height": 2661},{"type": "brick","time": 33795,"x": 1.0,"value": 16},{"type": "dot","time": 34050,"x": 0.6867509137756951,"value": 2},{"type": "brick","time": 34305,"x": 0.0,"value": 16},{"type": "brick","time": 34560,"x": 0.0,"value": 6},{"type": "dot","time": 34815,"x": 0.3579457570651994,"value": 9},{"type": "brick","time": 35070,"x": 0.3333333333333333,"value": 12},{"type": "dot","time": 35325,"x": 0.09973444075154714,"value": 3},{"type": "dot","time": 35580,"x": 0.34165172612859906,"value": 4},{"type": "dot","time": 35835,"x": 0.9409135533425106,"value": 3},{"type": "brick","time": 36090,"x": 0.0,"value": 12},{"type": "dot","time": 36345,"x": 0.5933654372513554,"value": 5},{"type": "dot","time": 36600,"x": 0.47699378414981486,"value": 5},{"type": "dot","time": 36855,"x": 0.8768573389526615,"value": 6},{"type": "brick","time": 37110,"x": 0.3333333333333333,"value": 11},{"type": "doubleup","time": 37365,"x": 0.7179199032684036},{"type": "barrier","time": 37620,"x": 0.75,"height": 410},{"type": "dot","time": 37875,"x": 0.25736409533924287,"value": 3},{"type": "brick","time": 38130,"x": 0.6666666666666666,"value": 6},{"type": "barrier","time": 38385,"x": 0.75,"height": 788},{"type": "brick","time": 38640,"x": 1.0,"value": 1},{"type": "dot","time": 38895,"x": 0.8747017989118853,"value": 3},{"type": "dot","time": 39150,"x": 0.7765928707397719,"value": 6},{"type": "dot","time": 39405,"x": 0.29158856991494464,"value": 8},{"type": "brick","time": 39660,"x": 0.6666666666666666,"value": 9},{"type": "brick","time": 39915,"x": 0.6666666666666666,"value": 16},{"type": "slowdown","time": 40170,"x": 0.8847108451411079},{"type": "doubleup","time": 40425,"x": 0.9310254527184222},{"type": "brick","time": 40680,"x": 0.3333333333333333,"value": 3},{"type": "brick","time": 40935,"x": 1.0,"value": 12},{"type": "dot","time": 41190,"x": 0.2900322490234224,"value": 3},{"type": "dot","time": 41445,"x": 0.2531770154687707,"value": 8},{"type": "brick","time": 41700,"x": 0.3333333333333333,"value": 5},{"type": "barrier","time": 41955,"x": 0.75,"height": 2144},{"type": "dot","time": 42210,"x": 0.8760776916175181,"value": 3},{"type": "dot","time": 42465,"x": 0.47747043806331746,"value": 3},{"type": "drill","time": 42720,"x": 0.6649133596742804},{"type": "dot","time": 42975,"x": 0.9319314495723157,"value": 7},{"type": "dot","time": 43230,"x": 0.6723360262629057,"value": 8},{"type": "barrier","time": 43485,"x": 0.75,"height": 1254},{"type": "doubleup","time": 43740,"x": 0.02292774822442445},{"type": "brick","time": 43995,"x": 0.3333333333333333,"value": 17},{"type": "dot","time": 44250,"x": 0.9665247609873148,"value": 2},{"type": "dot","time": 44505,"x": 0.8113170871213824,"value": 3},{"type": "dot","time": 44760,"x": 0.9791402429145031,"value": 2},{"type": "dot","time": 45015,"x": 0.9380592951244708,"value": 2},{"type": "dot","time": 45270,"x": 0.6767414348648486,"value": 5},{"type": "barrier","time": 45525,"x": 0.75,"height": 1000},{"type": "barrier","time": 45525,"x": 1.0,"height": 1000},{"type": "dot","time": 45625,"x": 1.12,"value": 6},{"type": "brick","time": 46525,"x": 1.0,"value": 11},{"type": "brick","time": 46780,"x": 0.6666666666666666,"value": 15},{"type": "barrier","time": 47035,"x": 0.5,"height": 2234},{"type": "dot","time": 47290,"x": 0.09267506427272254,"value": 4},{"type": "dot","time": 47545,"x": 0.7949788660270397,"value": 6},{"type": "brick","time": 47800,"x": 0.0,"value": 1},{"type": "dot","time": 48055,"x": 0.45050731858284243,"value": 4},{"type": "brick","time": 48310,"x": 1.0,"value": 16},{"type": "brick","time": 48565,"x": 1.0,"value": 5},{"type": "dot","time": 48820,"x": 0.4553366688533269,"value": 9},{"type": "brick","time": 49075,"x": 0.3333333333333333,"value": 3},{"type": "brick","time": 49330,"x": 1.0,"value": 12},{"type": "brick","time": 49490,"x": 0.6666666666666666,"value": 6},{"type": "brick","time": 49650,"x": 0.3333333333333333,"value": 5},{"type": "brick","time": 49905,"x": 0.6666666666666666,"value": 13},{"type": "brick","time": 50160,"x": 0.3333333333333333,"value": 4},{"type": "dot","time": 50415,"x": 0.3884304224657915,"value": 5},{"type": "dot","time": 50670,"x": 0.44740600828210686,"value": 6},{"type": "brick","time": 50925,"x": 0.0,"value": 10},{"type": "dot","time": 51180,"x": 0.02622169734038371,"value": 2},{"type": "brick","time": 51435,"x": 0.6666666666666666,"value": 12},{"type": "dot","time": 51690,"x": 0.9322294458961777,"value": 3},{"type": "brick","time": 51945,"x": 0.0,"value": 3},{"type": "dot","time": 52200,"x": 0.13031342602689422,"value": 1},{"type": "brick","time": 52455,"x": 0.0,"value": 10},{"type": "dot","time": 52710,"x": 0.059391245740289755,"value": 2},{"type": "doubleup","time": 52965,"x": 0.3179481197468861},{"type": "brick","time": 53220,"x": 0.6666666666666666,"value": 2},{"type": "brick","time": 53475,"x": 1.0,"value": 10},{"type": "dot","time": 53730,"x": 0.641511460858509,"value": 3},{"type": "brick","time": 53985,"x": 0.3333333333333333,"value": 2},{"type": "dot","time": 54240,"x": 0.830069886521663,"value": 2},{"type": "slowdown","time": 54495,"x": 0.9258838865906195},{"type": "brick","time": 54750,"x": 1.0,"value": 6},{"type": "brick","time": 55005,"x": 1.0,"value": 15},{"type": "dot","time": 55260,"x": 0.7799514261946261,"value": 4},{"type": "dot","time": 55515,"x": 0.6092309961702522,"value": 1},{"type": "brick","time": 55770,"x": 0.0,"value": 1},{"type": "dot","time": 56025,"x": 0.7312091081464864,"value": 8},{"type": "brick","time": 56280,"x": 0.0,"value": 15},{"type": "brick","time": 56280,"x": 0.3333333333333333,"value": 12},{"type": "brick","time": 56280,"x": 0.6666666666666666,"value": 11},{"type": "brick","time": 56280,"x": 1.0,"value": 13},{"type": "dot","time": 56535,"x": 0.6676557891661067,"value": 5},{"type": "dot","time": 56790,"x": 0.1123964004971515,"value": 9},{"type": "dot","time": 57045,"x": 0.567308631433741,"value": 3},{"type": "dot","time": 57300,"x": 0.5490689741213501,"value": 2},{"type": "dot","time": 57555,"x": 0.9366938146478591,"value": 9},{"type": "dot","time": 57810,"x": 0.971637884804347,"value": 9},{"type": "dot","time": 58065,"x": 0.36149541786514106,"value": 5},{"type": "dot","time": 58320,"x": 0.14980993187980107,"value": 6},{"type": "brick","time": 58575,"x": 0.3333333333333333,"value": 20},{"type": "dot","time": 58830,"x": 0.26473106809015334,"value": 1},{"type": "brick","time": 59085,"x": 0.3333333333333333,"value": 18},{"type": "brick","time": 59340,"x": 0.3333333333333333,"value": 5},{"type": "barrier","time": 59595,"x": 0.5,"height": 912},{"type": "brick","time": 59850,"x": 0.6666666666666666,"value": 2},{"type": "brick","time": 60105,"x": 0.3333333333333333,"value": 9},{"type": "brick","time": 60360,"x": 0.0,"value": 8},{"type": "brick","time": 60615,"x": 0.3333333333333333,"value": 15},{"type": "dot","time": 60870,"x": 0.7360384993699571,"value": 5},{"type": "brick","time": 61125,"x": 0.0,"value": 3},{"type": "brick","time": 61380,"x": 1.0,"value": 15},{"type": "dot","time": 61635,"x": 0.518600602226522,"value": 5},{"type": "dot","time": 61890,"x": 0.6004174735735593,"value": 7},{"type": "dot","time": 62145,"x": 0.7726084932755554,"value": 4},{"type": "dot","time": 62400,"x": 0.4178538120089502,"value": 5},{"type": "dot","time": 62655,"x": 0.6692800117651763,"value": 6},{"type": "brick","time": 62910,"x": 0.0,"value": 1},{"type": "brick","time": 63165,"x": 0.0,"value": 11},{"type": "brick","time": 63165,"x": 0.3333333333333333,"value": 14},{"type": "brick","time": 63165,"x": 0.6666666666666666,"value": 17},{"type": "brick","time": 63165,"x": 1.0,"value": 2},{"type": "brick","time": 63420,"x": 0.0,"value": 2},{"type": "barrier","time": 63675,"x": 0.5,"height": 2039},{"type": "brick","time": 63930,"x": 0.3333333333333333,"value": 12},{"type": "brick","time": 64185,"x": 0.6666666666666666,"value": 11},{"type": "brick","time": 64440,"x": 1.0,"value": 2},{"type": "dot","time": 64695,"x": 0.4311495358543228,"value": 2},{"type": "brick","time": 64950,"x": 0.6666666666666666,"value": 18},{"type": "brick","time": 65205,"x": 1.0,"value": 17},{"type": "brick","time": 65460,"x": 1.0,"value": 3},{"type": "dot","time": 65715,"x": 0.026792138483965444,"value": 2},{"type": "brick","time": 65970,"x": 0.0,"value": 3},{"type": "dot","time": 66225,"x": 0.2749843024908539,"value": 8},{"type": "brick","time": 66480,"x": 0.0,"value": 8},{"type": "brick","time": 66735,"x": 0.0,"value": 18},{"type": "dot","time": 66990,"x": 0.20961545792970093,"value": 1},{"type": "dot","time": 67245,"x": 0.7726216535714399,"value": 1},{"type": "dot","time": 67500,"x": 0.9462303104693128,"value": 4},{"type": "brick","time": 67755,"x": 0.6666666666666666,"value": 4},{"type": "brick","time": 68010,"x": 0.3333333333333333,"value": 5},{"type": "brick","time": 68265,"x": 0.0,"value": 15},{"type": "brick","time": 68520,"x": 0.0,"value": 7},{"type": "brick","time": 68775,"x": 0.0,"value": 10},{"type": "dot","time": 69030,"x": 0.4273637970501123,"value": 3},{"type": "brick","time": 69285,"x": 0.6666666666666666,"value": 15},{"type": "barrier","time": 69540,"x": 0.5,"height": 1611},{"type": "dot","time": 69795,"x": 0.8962676153396133,"value": 1},{"type": "dot","time": 70050,"x": 0.8837309235632791,"value": 9},{"type": "dot","time": 70305,"x": 0.11591222786403599,"value": 9},{"type": "dot","time": 70560,"x": 0.7037032024083196,"value": 7},{"type": "brick","time": 70815,"x": 0.3333333333333333,"value": 11},{"type": "brick","time": 71070,"x": 0.0,"value": 1},{"type": "dot","time": 71325,"x": 0.7908584285560416,"value": 3},{"type": "dot","time": 71580,"x": 0.06970963836183786,"value": 6},{"type": "drill","time": 71835,"x": 0.29434344324876105},{"type": "brick","time": 72090,"x": 0.3333333333333333,"value": 7},{"type": "dot","time": 72345,"x": 0.04898330463355671,"value": 1},{"type": "brick","time": 72600,"x": 0.6666666666666666,"value": 5},{"type": "barrier","time": 72855,"x": 0.5,"height": 653},{"type": "dot","time": 73110,"x": 0.5027378260086584,"value": 4},{"type": "dot","time": 73365,"x": 0.009224479822094178,"value": 1},{"type": "dot","time": 73620,"x": 0.1503409192265942,"value": 8},{"type": "brick","time": 73875,"x": 0.0,"value": 11},{"type": "brick","time": 73875,"x": 0.3333333333333333,"value": 16},{"type": "brick","time": 73875,"x": 0.6666666666666666,"value": 5},{"type": "brick","time": 73875,"x": 1.0,"value": 5},{"type": "dot","time": 74130,"x": 0.423316298844864,"value": 2},{"type": "brick","time": 74385,"x": 1.0,"value": 19},{"type": "dot","time": 74640,"x": 0.2867833525226492,"value": 8},{"type": "slowdown","time": 74895,"x": 0.1425243766162544},{"type": "dot","time": 75150,"x": 0.4782344820506469,"value": 1},{"type": "slowdown","time": 75405,"x": 0.9366008266200544},{"type": "brick","time": 75660,"x": 0.0,"value": 8},{"type": "barrier","time": 75915,"x": 0.5,"height": 2478},{"type": "brick","time": 76170,"x": 0.0,"value": 10},{"type": "brick","time": 76425,"x": 0.0,"value": 14},{"type": "brick","time": 76425,"x": 0.3333333333333333,"value": 5},{"type": "brick","time": 76425,"x": 0.6666666666666666,"value": 18},{"type": "brick","time": 76425,"x": 1.0,"value": 16},{"type": "barrier","time": 76680,"x": 0.5,"height": 1366},{"type": "dot","time": 76935,"x": 0.37259310771508647,"value": 9},{"type": "dot","time": 77190,"x": 0.9330842439575354,"value": 3},{"type": "barrier","time": 77445,"x": 0.5,"height": 1637},{"type": "brick","time": 77700,"x": 1.0,"value": 12},{"type": "brick","time": 77860,"x": 0.6666666666666666,"value": 2},{"type": "brick","time": 78020,"x": 0.3333333333333333,"value": 8},{"type": "dot","time": 78275,"x": 0.8361927767515167,"value": 1},{"type": "dot","time": 78530,"x": 0.8534664369899605,"value": 3},{"type": "barrier","time": 78785,"x": 0.25,"height": 2433},{"type": "brick","time": 79040,"x": 0.0,"value": 17},{"type": "brick","time": 79295,"x": 0.6666666666666666,"value": 18},{"type": "barrier","time": 79550,"x": 0.0,"height": 1000},{"type": "barrier","time": 79550,"x": 0.25,"height": 1000},{"type": "dot","time": 79650,"x": 0.12,"value": 5},{"type": "brick","time": 80550,"x": 0.0,"value": 16},{"type": "brick","time": 80805,"x": 0.0,"value": 8},{"type": "dot","time": 81060,"x": 0.1898870758319421,"value": 1},{"type": "dot","time": 81315,"x": 0.1569315170411142,"value": 9}]}